seffaflik/__init__.py
seffaflik/_kimlik.py
seffaflik/__ortak/__anahtar.py
seffaflik/__ortak/__araclar.py
seffaflik/__ortak/__dogrulama.py
seffaflik/__ortak/__init__.py
seffaflik/__ortak/__parametreler.py
seffaflik/dogalgaz/__init__.py
seffaflik/dogalgaz/stp.py
seffaflik/elektrik/__init__.py
seffaflik/elektrik/iletim.py
seffaflik/elektrik/santraller.py
seffaflik/elektrik/tuketim.py
seffaflik/elektrik/uretim.py
seffaflik/elektrik/yekdem.py
seffaflik/elektrik/piyasalar/__init__.py
seffaflik/elektrik/piyasalar/dengesizlik.py
seffaflik/elektrik/piyasalar/dgp.py
seffaflik/elektrik/piyasalar/genel.py
seffaflik/elektrik/piyasalar/gip.py
seffaflik/elektrik/piyasalar/gop.py
seffaflik/elektrik/piyasalar/ia.py
seffaflik/elektrik/piyasalar/yanhizmetler.py
seffaflik-0.0.22.dist-info/LICENSE.txt
seffaflik-0.0.22.dist-info/METADATA
seffaflik-0.0.22.dist-info/WHEEL
seffaflik-0.0.22.dist-info/top_level.txt
seffaflik-0.0.22.dist-info/RECORD
