Metadata-Version: 2.1
Name: seffaflik
Version: 0.0.22
Summary: EPİAŞ tarafından Şeffaflık Platformunda yayımlanmakta olan verileri çekmek için tasarlanmış Python kütüphanesi
Home-page: https://github.com/nurisensoy/seffaflik
Author: Dr. Nuri Şensoy
Author-email: nurisensoy87@gmail.com
Keywords: seffaflik,transparency,Turkish Energy Markets
Classifier: Programming Language :: Python :: 3.6
Classifier: Programming Language :: Python :: 3.7
Classifier: Programming Language :: Python :: 3.8
Classifier: License :: OSI Approved :: MIT License
Classifier: Operating System :: OS Independent
Requires-Python: >=3.6
License-File: LICENSE.txt
Requires-Dist: requests
Requires-Dist: pandas
Requires-Dist: python-dateutil
Requires-Dist: beautifulsoup4
Requires-Dist: xlrd
